codegen/__init__.py
codegen/default_config.py
codegen/example_config.py
codegen/graphql_2_python.py
codegen/model_module.py
cuckoo/__init__.py
cuckoo/binary_tree_node.py
cuckoo/constants.py
cuckoo/cuckoo.py
cuckoo/delete.py
cuckoo/encoders.py
cuckoo/errors.py
cuckoo/finalizers.py
cuckoo/include.py
cuckoo/insert.py
cuckoo/mutation.py
cuckoo/query.py
cuckoo/root_node.py
cuckoo/update.py
cuckoo/utils.py
cuckoo/models/__init__.py
cuckoo/models/builtins.py
cuckoo/models/common.py
cuckoo/models/providers.py
cuckoo_hasura-0.2.0.dist-info/LICENSE
cuckoo_hasura-0.2.0.dist-info/METADATA
cuckoo_hasura-0.2.0.dist-info/WHEEL
cuckoo_hasura-0.2.0.dist-info/entry_points.txt
cuckoo_hasura-0.2.0.dist-info/top_level.txt
cuckoo_hasura-0.2.0.dist-info/RECORD
