Metadata-Version: 2.1
Name: cuckoo-hasura
Version: 0.2.0
Summary: An easy to use GraphQL query builder, optimized for Hasura.
Author-email: Kenta Fried <kenta.fried@gmail.com>
License: MIT License
Project-URL: Homepage, https://github.com/hotaru355/cuckoo-hasura
Project-URL: Bug Tracker, https://github.com/hotaru355/cuckoo-hasura/issues
Classifier: Programming Language :: Python :: 3
Classifier: License :: OSI Approved :: MIT License
Classifier: Operating System :: OS Independent
Requires-Python: >=3.9
License-File: LICENSE
Requires-Dist: httpx >=0.24.0
Requires-Dist: ijson >=3.0
Requires-Dist: orjson >=3.0.0
Requires-Dist: pydantic <2.0.0,>=1.0.0
Requires-Dist: tenacity >=8.0.0
Provides-Extra: codegen
Requires-Dist: case-converter >=1.1.0 ; extra == 'codegen'
Requires-Dist: graphql-core >=3.2.3 ; extra == 'codegen'
